[{"id":"taikai0","user":{"name":"宇部高専","handle":"TAIKAI"},"operationCount":139,"pairCount":256,"updateAt":"1970-01-01T00:00:00.296Z"},{"id":"taikai1","user":{"name":"久留米高専","handle":"TAIKAI"},"operationCount":185,"pairCount":256,"updateAt":"1970-01-01T00:00:00.221Z"},{"id":"taikai5","user":{"name":"鹿児島高専","handle":"TAIKAI"},"operationCount":204,"pairCount":256,"updateAt":"1970-01-01T00:00:00.265Z"},{"id":"taikai6","user":{"name":"長野高専","handle":"TAIKAI"},"operationCount":249,"pairCount":256,"updateAt":"1970-01-01T00:00:00.107Z"},{"id":"taikai2","user":{"name":"神山高専","handle":"TAIKAI"},"operationCount":391,"pairCount":256,"updateAt":"1970-01-01T00:00:00.085Z"},{"id":"taikai3","user":{"name":"大分高専","handle":"TAIKAI"},"operationCount":3180,"pairCount":256,"updateAt":"1970-01-01T00:00:00.097Z"},{"id":"taikai7","user":{"name":"津山高専","handle":"TAIKAI"},"operationCount":2930,"pairCount":170,"updateAt":"1970-01-01T00:00:00.241Z"},{"id":"taikai4","user":{"name":"函館高専","handle":"TAIKAI"},"operationCount":114,"pairCount":8,"updateAt":"1970-01-01T00:00:00.294Z"}]